douglas/__init__.py
douglas/douglas.py
telma/__init__.py
telma/setup.py
telma/telma.py
douglas-0.0.3.dist-info/METADATA
douglas-0.0.3.dist-info/WHEEL
douglas-0.0.3.dist-info/top_level.txt
douglas-0.0.3.dist-info/RECORD
